README.rst
setup.py
oerplib3/__init__.py
oerplib3/error.py
oerplib3/oerp.py
oerplib3.egg-info/PKG-INFO
oerplib3.egg-info/SOURCES.txt
oerplib3.egg-info/dependency_links.txt
oerplib3.egg-info/entry_points.txt
oerplib3.egg-info/not-zip-safe
oerplib3.egg-info/requires.txt
oerplib3.egg-info/top_level.txt
oerplib3/rpc/__init__.py
oerplib3/rpc/error.py
oerplib3/rpc/jsonrpclib.py
oerplib3/rpc/netrpclib.py
oerplib3/rpc/service.py
oerplib3/rpc/xmlrpclib_custom.py
oerplib3/service/__init__.py
oerplib3/service/common.py
oerplib3/service/db.py
oerplib3/service/wizard.py
oerplib3/service/inspect/__init__.py
oerplib3/service/inspect/dependencies.py
oerplib3/service/inspect/on_change.py
oerplib3/service/inspect/relations.py
oerplib3/service/osv/__init__.py
oerplib3/service/osv/browse.py
oerplib3/service/osv/fields.py
oerplib3/service/osv/osv.py
oerplib3/tools/__init__.py
oerplib3/tools/session.py